LICENSE
MANIFEST.in
README.md
quicktest.py
settings_test.py
setup.py
django_vkontakte_api.egg-info/PKG-INFO
django_vkontakte_api.egg-info/SOURCES.txt
django_vkontakte_api.egg-info/dependency_links.txt
django_vkontakte_api.egg-info/not-zip-safe
django_vkontakte_api.egg-info/requires.txt
django_vkontakte_api.egg-info/top_level.txt
vkontakte_api/__init__.py
vkontakte_api/__init__.pyc
vkontakte_api/admin.py
vkontakte_api/admin.pyc
vkontakte_api/api.py
vkontakte_api/api.pyc
vkontakte_api/decorators.py
vkontakte_api/decorators.pyc
vkontakte_api/exceptions.py
vkontakte_api/exceptions.pyc
vkontakte_api/factories.py
vkontakte_api/factories.pyc
vkontakte_api/fields.py
vkontakte_api/fields.pyc
vkontakte_api/mixins.py
vkontakte_api/mixins.pyc
vkontakte_api/models.py
vkontakte_api/models.pyc
vkontakte_api/parser.py
vkontakte_api/parser.pyc
vkontakte_api/signals.py
vkontakte_api/signals.pyc
vkontakte_api/tests.py
vkontakte_api/tests.pyc
vkontakte_api/utils.py
vkontakte_api/utils.pyc
vkontakte_api/widgets.py
vkontakte_api/widgets.pyc